django_media_cleaner/__init__.py
django_media_cleaner/code.py
django_media_cleaner-0.1.1.dist-info/METADATA
django_media_cleaner-0.1.1.dist-info/WHEEL
django_media_cleaner-0.1.1.dist-info/top_level.txt
django_media_cleaner-0.1.1.dist-info/RECORD
